parse_diqu/__init__.py
parse_diqu/list.json
parse_diqu/parse_diqu.py
parse_diqu/parse_diquxx.py
parse_diqu/parse_diquxxx.py
parse_diqu/xzqh_key_word.json
parse_diqu/公共区域
parse_time/__init__.py
parse_time/ggzy_extra_time.py
parse_time/not_ggzy_extra_time.py
parse_diqu-1.0.27.dist-info/METADATA
parse_diqu-1.0.27.dist-info/WHEEL
parse_diqu-1.0.27.dist-info/top_level.txt
parse_diqu-1.0.27.dist-info/RECORD
