Metadata-Version: 2.1
Name: parse-diqu
Version: 1.0.27
Summary: 深圳市筑龙科技的工作-解析地区编号
Home-page: https://github.com/lanmengfei/testdm
Author: lanmengfei
Author-email: 865377886@qq.com
License: UNKNOWN
Platform: UNKNOWN
Classifier: Environment :: Web Environment
Classifier: Intended Audience :: Developers
Classifier: Operating System :: OS Independent
Classifier: Topic :: Text Processing :: Indexing
Classifier: Topic :: Utilities
Classifier: Topic :: Internet
Classifier: Topic :: Software Development :: Libraries :: Python Modules
Classifier: Programming Language :: Python
Classifier: Programming Language :: Python :: 3
Classifier: Programming Language :: Python :: 3.5
Requires-Dist: jieba
Requires-Dist: beautifulsoup4 (>=4.6.3)
Requires-Dist: lmfscrap (>=1.1.0)
